concat/__init__.py
concat/__main__.py
concat/lex.py
concat/libconcat.py
concat/parse.py
concat/parsetab.py
concat/stdlib/__init__.py
concat/stdlib/builtins.py
concat/stdlib/random.py
concat/stdoverrides/__init__.py
concat/stdoverrides/builtintypes.py
concat/stdoverrides/random_.py
concat/tests/__init__.py
concat/tests/test_example_programs.py
concat/tests/test_parse.py
concat/tests/test_python_concat_interface.py
concat-0.1.2.dev1.dist-info/DESCRIPTION.rst
concat-0.1.2.dev1.dist-info/METADATA
concat-0.1.2.dev1.dist-info/RECORD
concat-0.1.2.dev1.dist-info/WHEEL
concat-0.1.2.dev1.dist-info/metadata.json
concat-0.1.2.dev1.dist-info/top_level.txt
