Metadata-Version: 1.1
Name: concat
Version: 0.1.2.dev1
Summary: An experimental concatenative Python-based programming language
Home-page: https://github.com/jmanuel1/concat
Author: Jason Manuel
Author-email: jama.indo@hotmail.com
License: MIT
Keywords: concatenative
Platform: UNKNOWN
Classifier: Development Status :: 3 - Alpha
Classifier: Intended Audience :: Developers
Classifier: Topic :: Software Development :: Interpreters
Classifier: License :: OSI Approved :: MIT License
Classifier: Programming Language :: Python :: 3.5
